pipegenie/__init__.py
pipegenie/_available_if.py
pipegenie/_classification_regression.py
pipegenie/base.py
pipegenie/pipeline.py
pipegenie/utils.py
pipegenie/voting.py
pipegenie/classification/__init__.py
pipegenie/classification/pipegenie_classifier.py
pipegenie/classification/assets/grammar-classification.xml
pipegenie/elite/__init__.py
pipegenie/elite/_elite.py
pipegenie/evolutionary/__init__.py
pipegenie/evolutionary/_individual.py
pipegenie/evolutionary/crossover.py
pipegenie/evolutionary/mutation.py
pipegenie/evolutionary/replacement.py
pipegenie/evolutionary/selection.py
pipegenie/exceptions/__init__.py
pipegenie/exceptions/errors.py
pipegenie/grammar/__init__.py
pipegenie/grammar/_grammar.py
pipegenie/grammar/parser.py
pipegenie/logging/__init__.py
pipegenie/logging/_logging.py
pipegenie/logging/_stats.py
pipegenie/metrics/__init__.py
pipegenie/metrics/_classification.py
pipegenie/metrics/_regression.py
pipegenie/model_selection/__init__.py
pipegenie/model_selection/_split.py
pipegenie/regression/__init__.py
pipegenie/regression/pipegenie_regressor.py
pipegenie/regression/assets/grammar-regression.xml
pipegenie/syntax_tree/__init__.py
pipegenie/syntax_tree/_encoding.py
pipegenie/syntax_tree/_primitive_set.py
pipegenie-0.8.0.dist-info/licenses/LICENSE
pipegenie-0.8.0.dist-info/METADATA
pipegenie-0.8.0.dist-info/WHEEL
pipegenie-0.8.0.dist-info/top_level.txt
pipegenie-0.8.0.dist-info/RECORD
