Metadata-Version: 2.4
Name: pipegenie
Version: 0.8.0
Summary: A Python package for generation and optimization of machine learning pipelines using an evolutionary algorithm
Author-email: HUMAINS Research Group <info@pipegenie.org>
License: MIT License – HUMAINS Research Group Attribution Variant
Project-URL: Homepage, http://pipegenie.org/
Project-URL: Source, https://github.com/PipeGenie/PipeGenie
Keywords: machine learning,pipeline,generation,optimization,evolutionary algorithm
Classifier: Development Status :: 4 - Beta
Classifier: Intended Audience :: Developers
Classifier: Intended Audience :: Science/Research
Classifier: License :: OSI Approved :: MIT License
Classifier: Operating System :: MacOS
Classifier: Operating System :: POSIX
Classifier: Operating System :: Microsoft :: Windows
Classifier: Operating System :: Unix
Classifier: Programming Language :: Python
Classifier: Programming Language :: Python :: 3
Classifier: Programming Language :: Python :: 3.12
Classifier: Topic :: Scientific/Engineering :: Artificial Intelligence
Classifier: Topic :: Software Development
Classifier: Topic :: Software Development :: Libraries :: Python Modules
Classifier: Typing :: Typed
Requires-Python: <3.13,>=3.10
License-File: LICENSE
Requires-Dist: numpy<2,>=1.26
Requires-Dist: loky>=3.4
Dynamic: license-file
